{
  "db_name": "SQLite",
  "query": "SELECT t.id as \"id!\", t.name as \"name!\", t.color as \"color!\", t.created_at as \"created_at!\"\n               FROM tags t\n               INNER JOIN function_output_tags fot ON t.id = fot.tag_id\n               WHERE fot.function_id = ?",
  "describe": {
    "columns": [
      {
        "name": "id!",
        "ordinal": 0,
        "type_info": "Text"
      },
      {
        "name": "name!",
        "ordinal": 1,
        "type_info": "Text"
      },
      {
        "name": "color!",
        "ordinal": 2,
        "type_info": "Text"
      },
      {
        "name": "created_at!",
        "ordinal": 3,
        "type_info": "Text"
      }
    ],
    "parameters": {
      "Right": 1
    },
    "nullable": [
      true,
      false,
      false,
      false
    ]
  },
  "hash": "0bc68be593c7f2ba1f7dd92c2500c8999331c3e9f5bd776c8a0a7c1348300f05"
}
